<?xml version="1.0" encoding="UTF-8"?>
<con:soapui-project id="8bae9e84-6f95-4f95-9d59-c63f431f6d40" activeEnvironment="Default" name="CountryInfoService" resourceRoot="" soapui-version="5.7.0" xmlns:con="http://eviware.com/soapui/config"><con:settings/><con:interface xsi:type="con:WsdlInterface" id="ef297383-d66f-4bd5-aa4e-03225a5ccf61" wsaVersion="NONE" name="CountryInfoServiceSoapBinding" type="wsdl" bindingName="{http://www.oorsprong.org/websamples.countryinfo}CountryInfoServiceSoapBinding" soapVersion="1_1" anonymous="optional" definition="file:/home/cedric/Scripts/Sample_App/CountryInfoService.wsdl" xmlns:xsi="http://www.w3.org/2001/XMLSchema-instance"><con:settings/><con:definitionCache type="TEXT" rootPart="file:/home/cedric/Scripts/Sample_App/CountryInfoService.wsdl"><con:part><con:url>file:/home/cedric/Scripts/Sample_App/CountryInfoService.wsdl</con:url><con:content><![CDATA[<definitions name="CountryInfoService" targetNamespace="http://www.oorsprong.org/websamples.countryinfo" xmlns="http://schemas.xmlsoap.org/wsdl/" xmlns:xs="http://www.w3.org/2001/XMLSchema" xmlns:soap="http://schemas.xmlsoap.org/wsdl/soap/" xmlns:soap12="http://schemas.xmlsoap.org/wsdl/soap12/" xmlns:tns="http://www.oorsprong.org/websamples.countryinfo">
  <types>
    <xs:schema elementFormDefault="qualified" targetNamespace="http://www.oorsprong.org/websamples.countryinfo">
      <xs:complexType name="tContinent">
        <xs:sequence>
          <xs:element name="sCode" type="xs:string"/>
          <xs:element name="sName" type="xs:string"/>
        </xs:sequence>
      </xs:complexType>
      <xs:complexType name="tCurrency">
        <xs:sequence>
          <xs:element name="sISOCode" type="xs:string"/>
          <xs:element name="sName" type="xs:string"/>
        </xs:sequence>
      </xs:complexType>
      <xs:complexType name="tCountryCodeAndName">
        <xs:sequence>
          <xs:element name="sISOCode" type="xs:string"/>
          <xs:element name="sName" type="xs:string"/>
        </xs:sequence>
      </xs:complexType>
      <xs:complexType name="tCountryCodeAndNameGroupedByContinent">
        <xs:sequence>
          <xs:element name="Continent" type="tns:tContinent"/>
          <xs:element name="CountryCodeAndNames" type="tns:ArrayOftCountryCodeAndName"/>
        </xs:sequence>
      </xs:complexType>
      <xs:complexType name="tCountryInfo">
        <xs:sequence>
          <xs:element name="sISOCode" type="xs:string"/>
          <xs:element name="sName" type="xs:string"/>
          <xs:element name="sCapitalCity" type="xs:string"/>
          <xs:element name="sPhoneCode" type="xs:string"/>
          <xs:element name="sContinentCode" type="xs:string"/>
          <xs:element name="sCurrencyISOCode" type="xs:string"/>
          <xs:element name="sCountryFlag" type="xs:string"/>
          <xs:element name="Languages" type="tns:ArrayOftLanguage"/>
        </xs:sequence>
      </xs:complexType>
      <xs:complexType name="tLanguage">
        <xs:sequence>
          <xs:element name="sISOCode" type="xs:string"/>
          <xs:element name="sName" type="xs:string"/>
        </xs:sequence>
      </xs:complexType>
      <xs:complexType name="ArrayOftCountryCodeAndName">
        <xs:sequence>
          <xs:element name="tCountryCodeAndName" type="tns:tCountryCodeAndName" minOccurs="0" maxOccurs="unbounded" nillable="true"/>
        </xs:sequence>
      </xs:complexType>
      <xs:complexType name="ArrayOftLanguage">
        <xs:sequence>
          <xs:element name="tLanguage" type="tns:tLanguage" minOccurs="0" maxOccurs="unbounded" nillable="true"/>
        </xs:sequence>
      </xs:complexType>
      <xs:complexType name="ArrayOftContinent">
        <xs:sequence>
          <xs:element name="tContinent" type="tns:tContinent" minOccurs="0" maxOccurs="unbounded" nillable="true"/>
        </xs:sequence>
      </xs:complexType>
      <xs:complexType name="ArrayOftCurrency">
        <xs:sequence>
          <xs:element name="tCurrency" type="tns:tCurrency" minOccurs="0" maxOccurs="unbounded" nillable="true"/>
        </xs:sequence>
      </xs:complexType>
      <xs:complexType name="ArrayOftCountryCodeAndNameGroupedByContinent">
        <xs:sequence>
          <xs:element name="tCountryCodeAndNameGroupedByContinent" type="tns:tCountryCodeAndNameGroupedByContinent" minOccurs="0" maxOccurs="unbounded" nillable="true"/>
        </xs:sequence>
      </xs:complexType>
      <xs:complexType name="ArrayOftCountryInfo">
        <xs:sequence>
          <xs:element name="tCountryInfo" type="tns:tCountryInfo" minOccurs="0" maxOccurs="unbounded" nillable="true"/>
        </xs:sequence>
      </xs:complexType>
      <xs:element name="ListOfContinentsByName">
        <xs:complexType>
          <xs:sequence/>
        </xs:complexType>
      </xs:element>
      <xs:element name="ListOfContinentsByNameResponse">
        <xs:complexType>
          <xs:sequence>
            <xs:element name="ListOfContinentsByNameResult" type="tns:ArrayOftContinent"/>
          </xs:sequence>
        </xs:complexType>
      </xs:element>
      <xs:element name="ListOfContinentsByCode">
        <xs:complexType>
          <xs:sequence/>
        </xs:complexType>
      </xs:element>
      <xs:element name="ListOfContinentsByCodeResponse">
        <xs:complexType>
          <xs:sequence>
            <xs:element name="ListOfContinentsByCodeResult" type="tns:ArrayOftContinent"/>
          </xs:sequence>
        </xs:complexType>
      </xs:element>
      <xs:element name="ListOfCurrenciesByName">
        <xs:complexType>
          <xs:sequence/>
        </xs:complexType>
      </xs:element>
      <xs:element name="ListOfCurrenciesByNameResponse">
        <xs:complexType>
          <xs:sequence>
            <xs:element name="ListOfCurrenciesByNameResult" type="tns:ArrayOftCurrency"/>
          </xs:sequence>
        </xs:complexType>
      </xs:element>
      <xs:element name="ListOfCurrenciesByCode">
        <xs:complexType>
          <xs:sequence/>
        </xs:complexType>
      </xs:element>
      <xs:element name="ListOfCurrenciesByCodeResponse">
        <xs:complexType>
          <xs:sequence>
            <xs:element name="ListOfCurrenciesByCodeResult" type="tns:ArrayOftCurrency"/>
          </xs:sequence>
        </xs:complexType>
      </xs:element>
      <xs:element name="CurrencyName">
        <xs:complexType>
          <xs:sequence>
            <xs:element name="sCurrencyISOCode" type="xs:string"/>
          </xs:sequence>
        </xs:complexType>
      </xs:element>
      <xs:element name="CurrencyNameResponse">
        <xs:complexType>
          <xs:sequence>
            <xs:element name="CurrencyNameResult" type="xs:string"/>
          </xs:sequence>
        </xs:complexType>
      </xs:element>
      <xs:element name="ListOfCountryNamesByCode">
        <xs:complexType>
          <xs:sequence/>
        </xs:complexType>
      </xs:element>
      <xs:element name="ListOfCountryNamesByCodeResponse">
        <xs:complexType>
          <xs:sequence>
            <xs:element name="ListOfCountryNamesByCodeResult" type="tns:ArrayOftCountryCodeAndName"/>
          </xs:sequence>
        </xs:complexType>
      </xs:element>
      <xs:element name="ListOfCountryNamesByName">
        <xs:complexType>
          <xs:sequence/>
        </xs:complexType>
      </xs:element>
      <xs:element name="ListOfCountryNamesByNameResponse">
        <xs:complexType>
          <xs:sequence>
            <xs:element name="ListOfCountryNamesByNameResult" type="tns:ArrayOftCountryCodeAndName"/>
          </xs:sequence>
        </xs:complexType>
      </xs:element>
      <xs:element name="ListOfCountryNamesGroupedByContinent">
        <xs:complexType>
          <xs:sequence/>
        </xs:complexType>
      </xs:element>
      <xs:element name="ListOfCountryNamesGroupedByContinentResponse">
        <xs:complexType>
          <xs:sequence>
            <xs:element name="ListOfCountryNamesGroupedByContinentResult" type="tns:ArrayOftCountryCodeAndNameGroupedByContinent"/>
          </xs:sequence>
        </xs:complexType>
      </xs:element>
      <xs:element name="CountryName">
        <xs:complexType>
          <xs:sequence>
            <xs:element name="sCountryISOCode" type="xs:string"/>
          </xs:sequence>
        </xs:complexType>
      </xs:element>
      <xs:element name="CountryNameResponse">
        <xs:complexType>
          <xs:sequence>
            <xs:element name="CountryNameResult" type="xs:string"/>
          </xs:sequence>
        </xs:complexType>
      </xs:element>
      <xs:element name="CountryISOCode">
        <xs:complexType>
          <xs:sequence>
            <xs:element name="sCountryName" type="xs:string"/>
          </xs:sequence>
        </xs:complexType>
      </xs:element>
      <xs:element name="CountryISOCodeResponse">
        <xs:complexType>
          <xs:sequence>
            <xs:element name="CountryISOCodeResult" type="xs:string"/>
          </xs:sequence>
        </xs:complexType>
      </xs:element>
      <xs:element name="CapitalCity">
        <xs:complexType>
          <xs:sequence>
            <xs:element name="sCountryISOCode" type="xs:string"/>
          </xs:sequence>
        </xs:complexType>
      </xs:element>
      <xs:element name="CapitalCityResponse">
        <xs:complexType>
          <xs:sequence>
            <xs:element name="CapitalCityResult" type="xs:string"/>
          </xs:sequence>
        </xs:complexType>
      </xs:element>
      <xs:element name="CountryCurrency">
        <xs:complexType>
          <xs:sequence>
            <xs:element name="sCountryISOCode" type="xs:string"/>
          </xs:sequence>
        </xs:complexType>
      </xs:element>
      <xs:element name="CountryCurrencyResponse">
        <xs:complexType>
          <xs:sequence>
            <xs:element name="CountryCurrencyResult" type="tns:tCurrency"/>
          </xs:sequence>
        </xs:complexType>
      </xs:element>
      <xs:element name="CountryFlag">
        <xs:complexType>
          <xs:sequence>
            <xs:element name="sCountryISOCode" type="xs:string"/>
          </xs:sequence>
        </xs:complexType>
      </xs:element>
      <xs:element name="CountryFlagResponse">
        <xs:complexType>
          <xs:sequence>
            <xs:element name="CountryFlagResult" type="xs:string"/>
          </xs:sequence>
        </xs:complexType>
      </xs:element>
      <xs:element name="CountryIntPhoneCode">
        <xs:complexType>
          <xs:sequence>
            <xs:element name="sCountryISOCode" type="xs:string"/>
          </xs:sequence>
        </xs:complexType>
      </xs:element>
      <xs:element name="CountryIntPhoneCodeResponse">
        <xs:complexType>
          <xs:sequence>
            <xs:element name="CountryIntPhoneCodeResult" type="xs:string"/>
          </xs:sequence>
        </xs:complexType>
      </xs:element>
      <xs:element name="FullCountryInfo">
        <xs:complexType>
          <xs:sequence>
            <xs:element name="sCountryISOCode" type="xs:string"/>
          </xs:sequence>
        </xs:complexType>
      </xs:element>
      <xs:element name="FullCountryInfoResponse">
        <xs:complexType>
          <xs:sequence>
            <xs:element name="FullCountryInfoResult" type="tns:tCountryInfo"/>
          </xs:sequence>
        </xs:complexType>
      </xs:element>
      <xs:element name="FullCountryInfoAllCountries">
        <xs:complexType>
          <xs:sequence/>
        </xs:complexType>
      </xs:element>
      <xs:element name="FullCountryInfoAllCountriesResponse">
        <xs:complexType>
          <xs:sequence>
            <xs:element name="FullCountryInfoAllCountriesResult" type="tns:ArrayOftCountryInfo"/>
          </xs:sequence>
        </xs:complexType>
      </xs:element>
      <xs:element name="CountriesUsingCurrency">
        <xs:complexType>
          <xs:sequence>
            <xs:element name="sISOCurrencyCode" type="xs:string"/>
          </xs:sequence>
        </xs:complexType>
      </xs:element>
      <xs:element name="CountriesUsingCurrencyResponse">
        <xs:complexType>
          <xs:sequence>
            <xs:element name="CountriesUsingCurrencyResult" type="tns:ArrayOftCountryCodeAndName"/>
          </xs:sequence>
        </xs:complexType>
      </xs:element>
      <xs:element name="ListOfLanguagesByName">
        <xs:complexType>
          <xs:sequence/>
        </xs:complexType>
      </xs:element>
      <xs:element name="ListOfLanguagesByNameResponse">
        <xs:complexType>
          <xs:sequence>
            <xs:element name="ListOfLanguagesByNameResult" type="tns:ArrayOftLanguage"/>
          </xs:sequence>
        </xs:complexType>
      </xs:element>
      <xs:element name="ListOfLanguagesByCode">
        <xs:complexType>
          <xs:sequence/>
        </xs:complexType>
      </xs:element>
      <xs:element name="ListOfLanguagesByCodeResponse">
        <xs:complexType>
          <xs:sequence>
            <xs:element name="ListOfLanguagesByCodeResult" type="tns:ArrayOftLanguage"/>
          </xs:sequence>
        </xs:complexType>
      </xs:element>
      <xs:element name="LanguageName">
        <xs:complexType>
          <xs:sequence>
            <xs:element name="sISOCode" type="xs:string"/>
          </xs:sequence>
        </xs:complexType>
      </xs:element>
      <xs:element name="LanguageNameResponse">
        <xs:complexType>
          <xs:sequence>
            <xs:element name="LanguageNameResult" type="xs:string"/>
          </xs:sequence>
        </xs:complexType>
      </xs:element>
      <xs:element name="LanguageISOCode">
        <xs:complexType>
          <xs:sequence>
            <xs:element name="sLanguageName" type="xs:string"/>
          </xs:sequence>
        </xs:complexType>
      </xs:element>
      <xs:element name="LanguageISOCodeResponse">
        <xs:complexType>
          <xs:sequence>
            <xs:element name="LanguageISOCodeResult" type="xs:string"/>
          </xs:sequence>
        </xs:complexType>
      </xs:element>
    </xs:schema>
  </types>
  <message name="ListOfContinentsByNameSoapRequest">
    <part name="parameters" element="tns:ListOfContinentsByName"/>
  </message>
  <message name="ListOfContinentsByNameSoapResponse">
    <part name="parameters" element="tns:ListOfContinentsByNameResponse"/>
  </message>
  <message name="ListOfContinentsByCodeSoapRequest">
    <part name="parameters" element="tns:ListOfContinentsByCode"/>
  </message>
  <message name="ListOfContinentsByCodeSoapResponse">
    <part name="parameters" element="tns:ListOfContinentsByCodeResponse"/>
  </message>
  <message name="ListOfCurrenciesByNameSoapRequest">
    <part name="parameters" element="tns:ListOfCurrenciesByName"/>
  </message>
  <message name="ListOfCurrenciesByNameSoapResponse">
    <part name="parameters" element="tns:ListOfCurrenciesByNameResponse"/>
  </message>
  <message name="ListOfCurrenciesByCodeSoapRequest">
    <part name="parameters" element="tns:ListOfCurrenciesByCode"/>
  </message>
  <message name="ListOfCurrenciesByCodeSoapResponse">
    <part name="parameters" element="tns:ListOfCurrenciesByCodeResponse"/>
  </message>
  <message name="CurrencyNameSoapRequest">
    <part name="parameters" element="tns:CurrencyName"/>
  </message>
  <message name="CurrencyNameSoapResponse">
    <part name="parameters" element="tns:CurrencyNameResponse"/>
  </message>
  <message name="ListOfCountryNamesByCodeSoapRequest">
    <part name="parameters" element="tns:ListOfCountryNamesByCode"/>
  </message>
  <message name="ListOfCountryNamesByCodeSoapResponse">
    <part name="parameters" element="tns:ListOfCountryNamesByCodeResponse"/>
  </message>
  <message name="ListOfCountryNamesByNameSoapRequest">
    <part name="parameters" element="tns:ListOfCountryNamesByName"/>
  </message>
  <message name="ListOfCountryNamesByNameSoapResponse">
    <part name="parameters" element="tns:ListOfCountryNamesByNameResponse"/>
  </message>
  <message name="ListOfCountryNamesGroupedByContinentSoapRequest">
    <part name="parameters" element="tns:ListOfCountryNamesGroupedByContinent"/>
  </message>
  <message name="ListOfCountryNamesGroupedByContinentSoapResponse">
    <part name="parameters" element="tns:ListOfCountryNamesGroupedByContinentResponse"/>
  </message>
  <message name="CountryNameSoapRequest">
    <part name="parameters" element="tns:CountryName"/>
  </message>
  <message name="CountryNameSoapResponse">
    <part name="parameters" element="tns:CountryNameResponse"/>
  </message>
  <message name="CountryISOCodeSoapRequest">
    <part name="parameters" element="tns:CountryISOCode"/>
  </message>
  <message name="CountryISOCodeSoapResponse">
    <part name="parameters" element="tns:CountryISOCodeResponse"/>
  </message>
  <message name="CapitalCitySoapRequest">
    <part name="parameters" element="tns:CapitalCity"/>
  </message>
  <message name="CapitalCitySoapResponse">
    <part name="parameters" element="tns:CapitalCityResponse"/>
  </message>
  <message name="CountryCurrencySoapRequest">
    <part name="parameters" element="tns:CountryCurrency"/>
  </message>
  <message name="CountryCurrencySoapResponse">
    <part name="parameters" element="tns:CountryCurrencyResponse"/>
  </message>
  <message name="CountryFlagSoapRequest">
    <part name="parameters" element="tns:CountryFlag"/>
  </message>
  <message name="CountryFlagSoapResponse">
    <part name="parameters" element="tns:CountryFlagResponse"/>
  </message>
  <message name="CountryIntPhoneCodeSoapRequest">
    <part name="parameters" element="tns:CountryIntPhoneCode"/>
  </message>
  <message name="CountryIntPhoneCodeSoapResponse">
    <part name="parameters" element="tns:CountryIntPhoneCodeResponse"/>
  </message>
  <message name="FullCountryInfoSoapRequest">
    <part name="parameters" element="tns:FullCountryInfo"/>
  </message>
  <message name="FullCountryInfoSoapResponse">
    <part name="parameters" element="tns:FullCountryInfoResponse"/>
  </message>
  <message name="FullCountryInfoAllCountriesSoapRequest">
    <part name="parameters" element="tns:FullCountryInfoAllCountries"/>
  </message>
  <message name="FullCountryInfoAllCountriesSoapResponse">
    <part name="parameters" element="tns:FullCountryInfoAllCountriesResponse"/>
  </message>
  <message name="CountriesUsingCurrencySoapRequest">
    <part name="parameters" element="tns:CountriesUsingCurrency"/>
  </message>
  <message name="CountriesUsingCurrencySoapResponse">
    <part name="parameters" element="tns:CountriesUsingCurrencyResponse"/>
  </message>
  <message name="ListOfLanguagesByNameSoapRequest">
    <part name="parameters" element="tns:ListOfLanguagesByName"/>
  </message>
  <message name="ListOfLanguagesByNameSoapResponse">
    <part name="parameters" element="tns:ListOfLanguagesByNameResponse"/>
  </message>
  <message name="ListOfLanguagesByCodeSoapRequest">
    <part name="parameters" element="tns:ListOfLanguagesByCode"/>
  </message>
  <message name="ListOfLanguagesByCodeSoapResponse">
    <part name="parameters" element="tns:ListOfLanguagesByCodeResponse"/>
  </message>
  <message name="LanguageNameSoapRequest">
    <part name="parameters" element="tns:LanguageName"/>
  </message>
  <message name="LanguageNameSoapResponse">
    <part name="parameters" element="tns:LanguageNameResponse"/>
  </message>
  <message name="LanguageISOCodeSoapRequest">
    <part name="parameters" element="tns:LanguageISOCode"/>
  </message>
  <message name="LanguageISOCodeSoapResponse">
    <part name="parameters" element="tns:LanguageISOCodeResponse"/>
  </message>
  <portType name="CountryInfoServiceSoapType">
    <operation name="ListOfContinentsByName">
      <documentation>Returns a list of continents ordered by name.</documentation>
      <input message="tns:ListOfContinentsByNameSoapRequest"/>
      <output message="tns:ListOfContinentsByNameSoapResponse"/>
    </operation>
    <operation name="ListOfContinentsByCode">
      <documentation>Returns a list of continents ordered by code.</documentation>
      <input message="tns:ListOfContinentsByCodeSoapRequest"/>
      <output message="tns:ListOfContinentsByCodeSoapResponse"/>
    </operation>
    <operation name="ListOfCurrenciesByName">
      <documentation>Returns a list of currencies ordered by name.</documentation>
      <input message="tns:ListOfCurrenciesByNameSoapRequest"/>
      <output message="tns:ListOfCurrenciesByNameSoapResponse"/>
    </operation>
    <operation name="ListOfCurrenciesByCode">
      <documentation>Returns a list of currencies ordered by code.</documentation>
      <input message="tns:ListOfCurrenciesByCodeSoapRequest"/>
      <output message="tns:ListOfCurrenciesByCodeSoapResponse"/>
    </operation>
    <operation name="CurrencyName">
      <documentation>Returns the name of the currency (if found)</documentation>
      <input message="tns:CurrencyNameSoapRequest"/>
      <output message="tns:CurrencyNameSoapResponse"/>
    </operation>
    <operation name="ListOfCountryNamesByCode">
      <documentation>Returns a list of all stored counties ordered by ISO code</documentation>
      <input message="tns:ListOfCountryNamesByCodeSoapRequest"/>
      <output message="tns:ListOfCountryNamesByCodeSoapResponse"/>
    </operation>
    <operation name="ListOfCountryNamesByName">
      <documentation>Returns a list of all stored counties ordered by country name</documentation>
      <input message="tns:ListOfCountryNamesByNameSoapRequest"/>
      <output message="tns:ListOfCountryNamesByNameSoapResponse"/>
    </operation>
    <operation name="ListOfCountryNamesGroupedByContinent">
      <documentation>Returns a list of all stored counties grouped per continent</documentation>
      <input message="tns:ListOfCountryNamesGroupedByContinentSoapRequest"/>
      <output message="tns:ListOfCountryNamesGroupedByContinentSoapResponse"/>
    </operation>
    <operation name="CountryName">
      <documentation>Searches the database for a country by the passed ISO country code</documentation>
      <input message="tns:CountryNameSoapRequest"/>
      <output message="tns:CountryNameSoapResponse"/>
    </operation>
    <operation name="CountryISOCode">
      <documentation>This function tries to found a country based on the passed country name.</documentation>
      <input message="tns:CountryISOCodeSoapRequest"/>
      <output message="tns:CountryISOCodeSoapResponse"/>
    </operation>
    <operation name="CapitalCity">
      <documentation>Returns the  name of the captial city for the passed country code</documentation>
      <input message="tns:CapitalCitySoapRequest"/>
      <output message="tns:CapitalCitySoapResponse"/>
    </operation>
    <operation name="CountryCurrency">
      <documentation>Returns the currency ISO code and name for the passed country ISO code</documentation>
      <input message="tns:CountryCurrencySoapRequest"/>
      <output message="tns:CountryCurrencySoapResponse"/>
    </operation>
    <operation name="CountryFlag">
      <documentation>Returns a link to a picture of the country flag</documentation>
      <input message="tns:CountryFlagSoapRequest"/>
      <output message="tns:CountryFlagSoapResponse"/>
    </operation>
    <operation name="CountryIntPhoneCode">
      <documentation>Returns the internation phone code for the passed ISO country code</documentation>
      <input message="tns:CountryIntPhoneCodeSoapRequest"/>
      <output message="tns:CountryIntPhoneCodeSoapResponse"/>
    </operation>
    <operation name="FullCountryInfo">
      <documentation>Returns a struct with all the stored country information. Pass the ISO country code</documentation>
      <input message="tns:FullCountryInfoSoapRequest"/>
      <output message="tns:FullCountryInfoSoapResponse"/>
    </operation>
    <operation name="FullCountryInfoAllCountries">
      <documentation>Returns an array with all countries and all the language information stored</documentation>
      <input message="tns:FullCountryInfoAllCountriesSoapRequest"/>
      <output message="tns:FullCountryInfoAllCountriesSoapResponse"/>
    </operation>
    <operation name="CountriesUsingCurrency">
      <documentation>Returns a list of all countries that use the same currency code. Pass a ISO currency code</documentation>
      <input message="tns:CountriesUsingCurrencySoapRequest"/>
      <output message="tns:CountriesUsingCurrencySoapResponse"/>
    </operation>
    <operation name="ListOfLanguagesByName">
      <documentation>Returns an array of languages ordered by name</documentation>
      <input message="tns:ListOfLanguagesByNameSoapRequest"/>
      <output message="tns:ListOfLanguagesByNameSoapResponse"/>
    </operation>
    <operation name="ListOfLanguagesByCode">
      <documentation>Returns an array of languages ordered by code</documentation>
      <input message="tns:ListOfLanguagesByCodeSoapRequest"/>
      <output message="tns:ListOfLanguagesByCodeSoapResponse"/>
    </operation>
    <operation name="LanguageName">
      <documentation>Find a language name based on the passed ISO language code</documentation>
      <input message="tns:LanguageNameSoapRequest"/>
      <output message="tns:LanguageNameSoapResponse"/>
    </operation>
    <operation name="LanguageISOCode">
      <documentation>Find a language ISO code based on the passed language name</documentation>
      <input message="tns:LanguageISOCodeSoapRequest"/>
      <output message="tns:LanguageISOCodeSoapResponse"/>
    </operation>
  </portType>
  <binding name="CountryInfoServiceSoapBinding" type="tns:CountryInfoServiceSoapType">
    <soap:binding style="document" transport="http://schemas.xmlsoap.org/soap/http"/>
    <operation name="ListOfContinentsByName">
      <soap:operation soapAction="" style="document"/>
      <input>
        <soap:body use="literal"/>
      </input>
      <output>
        <soap:body use="literal"/>
      </output>
    </operation>
    <operation name="ListOfContinentsByCode">
      <soap:operation soapAction="" style="document"/>
      <input>
        <soap:body use="literal"/>
      </input>
      <output>
        <soap:body use="literal"/>
      </output>
    </operation>
    <operation name="ListOfCurrenciesByName">
      <soap:operation soapAction="" style="document"/>
      <input>
        <soap:body use="literal"/>
      </input>
      <output>
        <soap:body use="literal"/>
      </output>
    </operation>
    <operation name="ListOfCurrenciesByCode">
      <soap:operation soapAction="" style="document"/>
      <input>
        <soap:body use="literal"/>
      </input>
      <output>
        <soap:body use="literal"/>
      </output>
    </operation>
    <operation name="CurrencyName">
      <soap:operation soapAction="" style="document"/>
      <input>
        <soap:body use="literal"/>
      </input>
      <output>
        <soap:body use="literal"/>
      </output>
    </operation>
    <operation name="ListOfCountryNamesByCode">
      <soap:operation soapAction="" style="document"/>
      <input>
        <soap:body use="literal"/>
      </input>
      <output>
        <soap:body use="literal"/>
      </output>
    </operation>
    <operation name="ListOfCountryNamesByName">
      <soap:operation soapAction="" style="document"/>
      <input>
        <soap:body use="literal"/>
      </input>
      <output>
        <soap:body use="literal"/>
      </output>
    </operation>
    <operation name="ListOfCountryNamesGroupedByContinent">
      <soap:operation soapAction="" style="document"/>
      <input>
        <soap:body use="literal"/>
      </input>
      <output>
        <soap:body use="literal"/>
      </output>
    </operation>
    <operation name="CountryName">
      <soap:operation soapAction="" style="document"/>
      <input>
        <soap:body use="literal"/>
      </input>
      <output>
        <soap:body use="literal"/>
      </output>
    </operation>
    <operation name="CountryISOCode">
      <soap:operation soapAction="" style="document"/>
      <input>
        <soap:body use="literal"/>
      </input>
      <output>
        <soap:body use="literal"/>
      </output>
    </operation>
    <operation name="CapitalCity">
      <soap:operation soapAction="" style="document"/>
      <input>
        <soap:body use="literal"/>
      </input>
      <output>
        <soap:body use="literal"/>
      </output>
    </operation>
    <operation name="CountryCurrency">
      <soap:operation soapAction="" style="document"/>
      <input>
        <soap:body use="literal"/>
      </input>
      <output>
        <soap:body use="literal"/>
      </output>
    </operation>
    <operation name="CountryFlag">
      <soap:operation soapAction="" style="document"/>
      <input>
        <soap:body use="literal"/>
      </input>
      <output>
        <soap:body use="literal"/>
      </output>
    </operation>
    <operation name="CountryIntPhoneCode">
      <soap:operation soapAction="" style="document"/>
      <input>
        <soap:body use="literal"/>
      </input>
      <output>
        <soap:body use="literal"/>
      </output>
    </operation>
    <operation name="FullCountryInfo">
      <soap:operation soapAction="" style="document"/>
      <input>
        <soap:body use="literal"/>
      </input>
      <output>
        <soap:body use="literal"/>
      </output>
    </operation>
    <operation name="FullCountryInfoAllCountries">
      <soap:operation soapAction="" style="document"/>
      <input>
        <soap:body use="literal"/>
      </input>
      <output>
        <soap:body use="literal"/>
      </output>
    </operation>
    <operation name="CountriesUsingCurrency">
      <soap:operation soapAction="" style="document"/>
      <input>
        <soap:body use="literal"/>
      </input>
      <output>
        <soap:body use="literal"/>
      </output>
    </operation>
    <operation name="ListOfLanguagesByName">
      <soap:operation soapAction="" style="document"/>
      <input>
        <soap:body use="literal"/>
      </input>
      <output>
        <soap:body use="literal"/>
      </output>
    </operation>
    <operation name="ListOfLanguagesByCode">
      <soap:operation soapAction="" style="document"/>
      <input>
        <soap:body use="literal"/>
      </input>
      <output>
        <soap:body use="literal"/>
      </output>
    </operation>
    <operation name="LanguageName">
      <soap:operation soapAction="" style="document"/>
      <input>
        <soap:body use="literal"/>
      </input>
      <output>
        <soap:body use="literal"/>
      </output>
    </operation>
    <operation name="LanguageISOCode">
      <soap:operation soapAction="" style="document"/>
      <input>
        <soap:body use="literal"/>
      </input>
      <output>
        <soap:body use="literal"/>
      </output>
    </operation>
  </binding>
  <binding name="CountryInfoServiceSoapBinding12" type="tns:CountryInfoServiceSoapType">
    <soap12:binding style="document" transport="http://schemas.xmlsoap.org/soap/http"/>
    <operation name="ListOfContinentsByName">
      <soap12:operation soapAction="" style="document"/>
      <input>
        <soap12:body use="literal"/>
      </input>
      <output>
        <soap12:body use="literal"/>
      </output>
    </operation>
    <operation name="ListOfContinentsByCode">
      <soap12:operation soapAction="" style="document"/>
      <input>
        <soap12:body use="literal"/>
      </input>
      <output>
        <soap12:body use="literal"/>
      </output>
    </operation>
    <operation name="ListOfCurrenciesByName">
      <soap12:operation soapAction="" style="document"/>
      <input>
        <soap12:body use="literal"/>
      </input>
      <output>
        <soap12:body use="literal"/>
      </output>
    </operation>
    <operation name="ListOfCurrenciesByCode">
      <soap12:operation soapAction="" style="document"/>
      <input>
        <soap12:body use="literal"/>
      </input>
      <output>
        <soap12:body use="literal"/>
      </output>
    </operation>
    <operation name="CurrencyName">
      <soap12:operation soapAction="" style="document"/>
      <input>
        <soap12:body use="literal"/>
      </input>
      <output>
        <soap12:body use="literal"/>
      </output>
    </operation>
    <operation name="ListOfCountryNamesByCode">
      <soap12:operation soapAction="" style="document"/>
      <input>
        <soap12:body use="literal"/>
      </input>
      <output>
        <soap12:body use="literal"/>
      </output>
    </operation>
    <operation name="ListOfCountryNamesByName">
      <soap12:operation soapAction="" style="document"/>
      <input>
        <soap12:body use="literal"/>
      </input>
      <output>
        <soap12:body use="literal"/>
      </output>
    </operation>
    <operation name="ListOfCountryNamesGroupedByContinent">
      <soap12:operation soapAction="" style="document"/>
      <input>
        <soap12:body use="literal"/>
      </input>
      <output>
        <soap12:body use="literal"/>
      </output>
    </operation>
    <operation name="CountryName">
      <soap12:operation soapAction="" style="document"/>
      <input>
        <soap12:body use="literal"/>
      </input>
      <output>
        <soap12:body use="literal"/>
      </output>
    </operation>
    <operation name="CountryISOCode">
      <soap12:operation soapAction="" style="document"/>
      <input>
        <soap12:body use="literal"/>
      </input>
      <output>
        <soap12:body use="literal"/>
      </output>
    </operation>
    <operation name="CapitalCity">
      <soap12:operation soapAction="" style="document"/>
      <input>
        <soap12:body use="literal"/>
      </input>
      <output>
        <soap12:body use="literal"/>
      </output>
    </operation>
    <operation name="CountryCurrency">
      <soap12:operation soapAction="" style="document"/>
      <input>
        <soap12:body use="literal"/>
      </input>
      <output>
        <soap12:body use="literal"/>
      </output>
    </operation>
    <operation name="CountryFlag">
      <soap12:operation soapAction="" style="document"/>
      <input>
        <soap12:body use="literal"/>
      </input>
      <output>
        <soap12:body use="literal"/>
      </output>
    </operation>
    <operation name="CountryIntPhoneCode">
      <soap12:operation soapAction="" style="document"/>
      <input>
        <soap12:body use="literal"/>
      </input>
      <output>
        <soap12:body use="literal"/>
      </output>
    </operation>
    <operation name="FullCountryInfo">
      <soap12:operation soapAction="" style="document"/>
      <input>
        <soap12:body use="literal"/>
      </input>
      <output>
        <soap12:body use="literal"/>
      </output>
    </operation>
    <operation name="FullCountryInfoAllCountries">
      <soap12:operation soapAction="" style="document"/>
      <input>
        <soap12:body use="literal"/>
      </input>
      <output>
        <soap12:body use="literal"/>
      </output>
    </operation>
    <operation name="CountriesUsingCurrency">
      <soap12:operation soapAction="" style="document"/>
      <input>
        <soap12:body use="literal"/>
      </input>
      <output>
        <soap12:body use="literal"/>
      </output>
    </operation>
    <operation name="ListOfLanguagesByName">
      <soap12:operation soapAction="" style="document"/>
      <input>
        <soap12:body use="literal"/>
      </input>
      <output>
        <soap12:body use="literal"/>
      </output>
    </operation>
    <operation name="ListOfLanguagesByCode">
      <soap12:operation soapAction="" style="document"/>
      <input>
        <soap12:body use="literal"/>
      </input>
      <output>
        <soap12:body use="literal"/>
      </output>
    </operation>
    <operation name="LanguageName">
      <soap12:operation soapAction="" style="document"/>
      <input>
        <soap12:body use="literal"/>
      </input>
      <output>
        <soap12:body use="literal"/>
      </output>
    </operation>
    <operation name="LanguageISOCode">
      <soap12:operation soapAction="" style="document"/>
      <input>
        <soap12:body use="literal"/>
      </input>
      <output>
        <soap12:body use="literal"/>
      </output>
    </operation>
  </binding>
  <service name="CountryInfoService">
    <documentation>This DataFlex Web Service opens up country information. 2 letter ISO codes are used for Country code. There are functions to retrieve the used Currency, Language, Capital City, Continent and Telephone code.</documentation>
    <port name="CountryInfoServiceSoap" binding="tns:CountryInfoServiceSoapBinding">
      <soap:address location="http://webservices.oorsprong.org/websamples.countryinfo/CountryInfoService.wso"/>
    </port>
    <port name="CountryInfoServiceSoap12" binding="tns:CountryInfoServiceSoapBinding12">
      <soap12:address location="http://webservices.oorsprong.org/websamples.countryinfo/CountryInfoService.wso"/>
    </port>
  </service>
</definitions>]]></con:content><con:type>http://schemas.xmlsoap.org/wsdl/</con:type></con:part></con:definitionCache><con:endpoints><con:endpoint>http://webservices.oorsprong.org/websamples.countryinfo/CountryInfoService.wso</con:endpoint></con:endpoints><con:operation id="49b196a0-6237-4d3f-a09a-562b392d4fc0" isOneWay="false" action="" name="CapitalCity" bindingOperationName="CapitalCity" type="Request-Response" inputName="" receivesAttachments="false" sendsAttachments="false" anonymous="optional"><con:settings/><con:call id="f53f530d-38cc-4ffe-9be5-8876e9a687c3" name="Request 1"><con:settings><con:setting id="com.eviware.soapui.impl.wsdl.WsdlRequest@request-headers">&lt;xml-fragment/></con:setting></con:settings><con:encoding>UTF-8</con:encoding><con:endpoint>http://webservices.oorsprong.org/websamples.countryinfo/CountryInfoService.wso</con:endpoint><con:request><![CDATA[<soapenv:Envelope xmlns:soapenv="http://schemas.xmlsoap.org/soap/envelope/" xmlns:web="http://www.oorsprong.org/websamples.countryinfo">
   <soapenv:Header/>
   <soapenv:Body>
      <web:CapitalCity>
         <web:sCountryISOCode>IN</web:sCountryISOCode>
      </web:CapitalCity>
   </soapenv:Body>
</soapenv:Envelope>]]></con:request><con:credentials><con:authType>No Authorization</con:authType></con:credentials><con:jmsConfig JMSDeliveryMode="PERSISTENT"/><con:jmsPropertyConfig/><con:wsaConfig mustUnderstand="NONE" version="200508" action="http://www.oorsprong.org/websamples.countryinfo/CountryInfoServiceSoapType/CapitalCityRequest"/><con:wsrmConfig version="1.2"/></con:call></con:operation><con:operation id="a74d7a6a-1e35-4009-abd5-29d433ab962e" isOneWay="false" action="" name="CountriesUsingCurrency" bindingOperationName="CountriesUsingCurrency" type="Request-Response" inputName="" receivesAttachments="false" sendsAttachments="false" anonymous="optional"><con:settings/><con:call id="e1bc5809-3bbb-4db4-bdae-34c82bd9cce4" name="Request 1"><con:settings/><con:encoding>UTF-8</con:encoding><con:endpoint>http://webservices.oorsprong.org/websamples.countryinfo/CountryInfoService.wso</con:endpoint><con:request><![CDATA[<soapenv:Envelope xmlns:soapenv="http://schemas.xmlsoap.org/soap/envelope/" xmlns:web="http://www.oorsprong.org/websamples.countryinfo">
   <soapenv:Header/>
   <soapenv:Body>
      <web:CountriesUsingCurrency>
         <web:sISOCurrencyCode>?</web:sISOCurrencyCode>
      </web:CountriesUsingCurrency>
   </soapenv:Body>
</soapenv:Envelope>]]></con:request><con:wsaConfig mustUnderstand="NONE" version="200508" action="http://www.oorsprong.org/websamples.countryinfo/CountryInfoServiceSoapType/CountriesUsingCurrencyRequest"/></con:call></con:operation><con:operation id="96dffb1f-c0ec-410b-a442-89b8f9070989" isOneWay="false" action="" name="CountryCurrency" bindingOperationName="CountryCurrency" type="Request-Response" inputName="" receivesAttachments="false" sendsAttachments="false" anonymous="optional"><con:settings/><con:call id="45539434-afbe-46f0-bf59-8d2d32f98ca3" name="Request 1"><con:settings/><con:encoding>UTF-8</con:encoding><con:endpoint>http://webservices.oorsprong.org/websamples.countryinfo/CountryInfoService.wso</con:endpoint><con:request><![CDATA[<soapenv:Envelope xmlns:soapenv="http://schemas.xmlsoap.org/soap/envelope/" xmlns:web="http://www.oorsprong.org/websamples.countryinfo">
   <soapenv:Header/>
   <soapenv:Body>
      <web:CountryCurrency>
         <web:sCountryISOCode>?</web:sCountryISOCode>
      </web:CountryCurrency>
   </soapenv:Body>
</soapenv:Envelope>]]></con:request><con:wsaConfig mustUnderstand="NONE" version="200508" action="http://www.oorsprong.org/websamples.countryinfo/CountryInfoServiceSoapType/CountryCurrencyRequest"/></con:call></con:operation><con:operation id="35e9fe98-495c-48f9-ace6-f79b7322b89b" isOneWay="false" action="" name="CountryFlag" bindingOperationName="CountryFlag" type="Request-Response" inputName="" receivesAttachments="false" sendsAttachments="false" anonymous="optional"><con:settings/><con:call id="8e6894fd-6093-448e-be82-970c5b8dc792" name="Request 1"><con:settings/><con:encoding>UTF-8</con:encoding><con:endpoint>http://webservices.oorsprong.org/websamples.countryinfo/CountryInfoService.wso</con:endpoint><con:request><![CDATA[<soapenv:Envelope xmlns:soapenv="http://schemas.xmlsoap.org/soap/envelope/" xmlns:web="http://www.oorsprong.org/websamples.countryinfo">
   <soapenv:Header/>
   <soapenv:Body>
      <web:CountryFlag>
         <web:sCountryISOCode>?</web:sCountryISOCode>
      </web:CountryFlag>
   </soapenv:Body>
</soapenv:Envelope>]]></con:request><con:wsaConfig mustUnderstand="NONE" version="200508" action="http://www.oorsprong.org/websamples.countryinfo/CountryInfoServiceSoapType/CountryFlagRequest"/></con:call></con:operation><con:operation id="fc171938-6c6b-4a63-958f-aa92beaa612f" isOneWay="false" action="" name="CountryIntPhoneCode" bindingOperationName="CountryIntPhoneCode" type="Request-Response" inputName="" receivesAttachments="false" sendsAttachments="false" anonymous="optional"><con:settings/><con:call id="8932c0f3-514c-46f4-b456-c5bcba9e93e5" name="Request 1"><con:settings/><con:encoding>UTF-8</con:encoding><con:endpoint>http://webservices.oorsprong.org/websamples.countryinfo/CountryInfoService.wso</con:endpoint><con:request><![CDATA[<soapenv:Envelope xmlns:soapenv="http://schemas.xmlsoap.org/soap/envelope/" xmlns:web="http://www.oorsprong.org/websamples.countryinfo">
   <soapenv:Header/>
   <soapenv:Body>
      <web:CountryIntPhoneCode>
         <web:sCountryISOCode>?</web:sCountryISOCode>
      </web:CountryIntPhoneCode>
   </soapenv:Body>
</soapenv:Envelope>]]></con:request><con:wsaConfig mustUnderstand="NONE" version="200508" action="http://www.oorsprong.org/websamples.countryinfo/CountryInfoServiceSoapType/CountryIntPhoneCodeRequest"/></con:call></con:operation><con:operation id="c658cca8-b39d-4699-80da-b223498ae871" isOneWay="false" action="" name="CountryISOCode" bindingOperationName="CountryISOCode" type="Request-Response" inputName="" receivesAttachments="false" sendsAttachments="false" anonymous="optional"><con:settings/><con:call id="eb499904-f1d3-40eb-8bd3-16ea89f2678d" name="Request 1"><con:settings/><con:encoding>UTF-8</con:encoding><con:endpoint>http://webservices.oorsprong.org/websamples.countryinfo/CountryInfoService.wso</con:endpoint><con:request><![CDATA[<soapenv:Envelope xmlns:soapenv="http://schemas.xmlsoap.org/soap/envelope/" xmlns:web="http://www.oorsprong.org/websamples.countryinfo">
   <soapenv:Header/>
   <soapenv:Body>
      <web:CountryISOCode>
         <web:sCountryName>?</web:sCountryName>
      </web:CountryISOCode>
   </soapenv:Body>
</soapenv:Envelope>]]></con:request><con:wsaConfig mustUnderstand="NONE" version="200508" action="http://www.oorsprong.org/websamples.countryinfo/CountryInfoServiceSoapType/CountryISOCodeRequest"/></con:call></con:operation><con:operation id="469e5b5b-5a6c-4be2-996c-36a934462a77" isOneWay="false" action="" name="CountryName" bindingOperationName="CountryName" type="Request-Response" inputName="" receivesAttachments="false" sendsAttachments="false" anonymous="optional"><con:settings/><con:call id="315c9ff7-cfc7-47cf-94cb-00eb43db1d77" name="Request 1"><con:settings/><con:encoding>UTF-8</con:encoding><con:endpoint>http://webservices.oorsprong.org/websamples.countryinfo/CountryInfoService.wso</con:endpoint><con:request><![CDATA[<soapenv:Envelope xmlns:soapenv="http://schemas.xmlsoap.org/soap/envelope/" xmlns:web="http://www.oorsprong.org/websamples.countryinfo">
   <soapenv:Header/>
   <soapenv:Body>
      <web:CountryName>
         <web:sCountryISOCode>?</web:sCountryISOCode>
      </web:CountryName>
   </soapenv:Body>
</soapenv:Envelope>]]></con:request><con:wsaConfig mustUnderstand="NONE" version="200508" action="http://www.oorsprong.org/websamples.countryinfo/CountryInfoServiceSoapType/CountryNameRequest"/></con:call></con:operation><con:operation id="4edb1a27-ebcc-4873-b1e9-492975d04b9e" isOneWay="false" action="" name="CurrencyName" bindingOperationName="CurrencyName" type="Request-Response" inputName="" receivesAttachments="false" sendsAttachments="false" anonymous="optional"><con:settings/><con:call id="32a93d19-29f9-4e42-98c5-6daf35486f3d" name="Request 1"><con:settings/><con:encoding>UTF-8</con:encoding><con:endpoint>http://webservices.oorsprong.org/websamples.countryinfo/CountryInfoService.wso</con:endpoint><con:request><![CDATA[<soapenv:Envelope xmlns:soapenv="http://schemas.xmlsoap.org/soap/envelope/" xmlns:web="http://www.oorsprong.org/websamples.countryinfo">
   <soapenv:Header/>
   <soapenv:Body>
      <web:CurrencyName>
         <web:sCurrencyISOCode>?</web:sCurrencyISOCode>
      </web:CurrencyName>
   </soapenv:Body>
</soapenv:Envelope>]]></con:request><con:wsaConfig mustUnderstand="NONE" version="200508" action="http://www.oorsprong.org/websamples.countryinfo/CountryInfoServiceSoapType/CurrencyNameRequest"/></con:call></con:operation><con:operation id="20c4a1f5-e857-4a7c-b0ec-93752408bb66" isOneWay="false" action="" name="FullCountryInfo" bindingOperationName="FullCountryInfo" type="Request-Response" inputName="" receivesAttachments="false" sendsAttachments="false" anonymous="optional"><con:settings/><con:call id="a76de3c6-49ee-4ec4-897a-a7ad9891104f" name="Request 1"><con:settings/><con:encoding>UTF-8</con:encoding><con:endpoint>http://webservices.oorsprong.org/websamples.countryinfo/CountryInfoService.wso</con:endpoint><con:request><![CDATA[<soapenv:Envelope xmlns:soapenv="http://schemas.xmlsoap.org/soap/envelope/" xmlns:web="http://www.oorsprong.org/websamples.countryinfo">
   <soapenv:Header/>
   <soapenv:Body>
      <web:FullCountryInfo>
         <web:sCountryISOCode>?</web:sCountryISOCode>
      </web:FullCountryInfo>
   </soapenv:Body>
</soapenv:Envelope>]]></con:request><con:wsaConfig mustUnderstand="NONE" version="200508" action="http://www.oorsprong.org/websamples.countryinfo/CountryInfoServiceSoapType/FullCountryInfoRequest"/></con:call></con:operation><con:operation id="0ad7f48a-c680-490a-b744-e92d28aa0b23" isOneWay="false" action="" name="FullCountryInfoAllCountries" bindingOperationName="FullCountryInfoAllCountries" type="Request-Response" inputName="" receivesAttachments="false" sendsAttachments="false" anonymous="optional"><con:settings/><con:call id="e688a723-b377-4b23-be0b-34aa89d1144d" name="Request 1"><con:settings/><con:encoding>UTF-8</con:encoding><con:endpoint>http://webservices.oorsprong.org/websamples.countryinfo/CountryInfoService.wso</con:endpoint><con:request><![CDATA[<soapenv:Envelope xmlns:soapenv="http://schemas.xmlsoap.org/soap/envelope/" xmlns:web="http://www.oorsprong.org/websamples.countryinfo">
   <soapenv:Header/>
   <soapenv:Body>
      <web:FullCountryInfoAllCountries/>
   </soapenv:Body>
</soapenv:Envelope>]]></con:request><con:wsaConfig mustUnderstand="NONE" version="200508" action="http://www.oorsprong.org/websamples.countryinfo/CountryInfoServiceSoapType/FullCountryInfoAllCountriesRequest"/></con:call></con:operation><con:operation id="a341376c-c4b7-4c88-aefc-3943fbd52e80" isOneWay="false" action="" name="LanguageISOCode" bindingOperationName="LanguageISOCode" type="Request-Response" inputName="" receivesAttachments="false" sendsAttachments="false" anonymous="optional"><con:settings/><con:call id="4ec001d5-a1fd-4aac-9d3c-e248c46a9db4" name="Request 1"><con:settings/><con:encoding>UTF-8</con:encoding><con:endpoint>http://webservices.oorsprong.org/websamples.countryinfo/CountryInfoService.wso</con:endpoint><con:request><![CDATA[<soapenv:Envelope xmlns:soapenv="http://schemas.xmlsoap.org/soap/envelope/" xmlns:web="http://www.oorsprong.org/websamples.countryinfo">
   <soapenv:Header/>
   <soapenv:Body>
      <web:LanguageISOCode>
         <web:sLanguageName>?</web:sLanguageName>
      </web:LanguageISOCode>
   </soapenv:Body>
</soapenv:Envelope>]]></con:request><con:wsaConfig mustUnderstand="NONE" version="200508" action="http://www.oorsprong.org/websamples.countryinfo/CountryInfoServiceSoapType/LanguageISOCodeRequest"/></con:call></con:operation><con:operation id="67d1ba16-0c57-4c9e-bfe7-8e6d4ef5b7f7" isOneWay="false" action="" name="LanguageName" bindingOperationName="LanguageName" type="Request-Response" inputName="" receivesAttachments="false" sendsAttachments="false" anonymous="optional"><con:settings/><con:call id="780f43fb-ac91-42f5-8b7a-b25911307be8" name="Request 1"><con:settings/><con:encoding>UTF-8</con:encoding><con:endpoint>http://webservices.oorsprong.org/websamples.countryinfo/CountryInfoService.wso</con:endpoint><con:request><![CDATA[<soapenv:Envelope xmlns:soapenv="http://schemas.xmlsoap.org/soap/envelope/" xmlns:web="http://www.oorsprong.org/websamples.countryinfo">
   <soapenv:Header/>
   <soapenv:Body>
      <web:LanguageName>
         <web:sISOCode>?</web:sISOCode>
      </web:LanguageName>
   </soapenv:Body>
</soapenv:Envelope>]]></con:request><con:wsaConfig mustUnderstand="NONE" version="200508" action="http://www.oorsprong.org/websamples.countryinfo/CountryInfoServiceSoapType/LanguageNameRequest"/></con:call></con:operation><con:operation id="bfa2ccec-5cfd-4ba9-a699-8edeb5a03ad2" isOneWay="false" action="" name="ListOfContinentsByCode" bindingOperationName="ListOfContinentsByCode" type="Request-Response" inputName="" receivesAttachments="false" sendsAttachments="false" anonymous="optional"><con:settings/><con:call id="d508ecd6-f4fb-4c6b-b5f2-9d5b268b5451" name="Request 1"><con:settings/><con:encoding>UTF-8</con:encoding><con:endpoint>http://webservices.oorsprong.org/websamples.countryinfo/CountryInfoService.wso</con:endpoint><con:request><![CDATA[<soapenv:Envelope xmlns:soapenv="http://schemas.xmlsoap.org/soap/envelope/" xmlns:web="http://www.oorsprong.org/websamples.countryinfo">
   <soapenv:Header/>
   <soapenv:Body>
      <web:ListOfContinentsByCode/>
   </soapenv:Body>
</soapenv:Envelope>]]></con:request><con:wsaConfig mustUnderstand="NONE" version="200508" action="http://www.oorsprong.org/websamples.countryinfo/CountryInfoServiceSoapType/ListOfContinentsByCodeRequest"/></con:call></con:operation><con:operation id="f953339e-7fd3-461b-a63b-0c5c36079233" isOneWay="false" action="" name="ListOfContinentsByName" bindingOperationName="ListOfContinentsByName" type="Request-Response" inputName="" receivesAttachments="false" sendsAttachments="false" anonymous="optional"><con:settings/><con:call id="8c8d7f9c-b4ae-4067-853e-6c48ef7bbf69" name="Request 1"><con:settings/><con:encoding>UTF-8</con:encoding><con:endpoint>http://webservices.oorsprong.org/websamples.countryinfo/CountryInfoService.wso</con:endpoint><con:request><![CDATA[<soapenv:Envelope xmlns:soapenv="http://schemas.xmlsoap.org/soap/envelope/" xmlns:web="http://www.oorsprong.org/websamples.countryinfo">
   <soapenv:Header/>
   <soapenv:Body>
      <web:ListOfContinentsByName/>
   </soapenv:Body>
</soapenv:Envelope>]]></con:request><con:wsaConfig mustUnderstand="NONE" version="200508" action="http://www.oorsprong.org/websamples.countryinfo/CountryInfoServiceSoapType/ListOfContinentsByNameRequest"/></con:call></con:operation><con:operation id="341589e9-891e-432d-a1a5-031d567415d6" isOneWay="false" action="" name="ListOfCountryNamesByCode" bindingOperationName="ListOfCountryNamesByCode" type="Request-Response" inputName="" receivesAttachments="false" sendsAttachments="false" anonymous="optional"><con:settings/><con:call id="ad1ed952-9727-4ee9-9e2d-bd1b640725f2" name="Request 1"><con:settings/><con:encoding>UTF-8</con:encoding><con:endpoint>http://webservices.oorsprong.org/websamples.countryinfo/CountryInfoService.wso</con:endpoint><con:request><![CDATA[<soapenv:Envelope xmlns:soapenv="http://schemas.xmlsoap.org/soap/envelope/" xmlns:web="http://www.oorsprong.org/websamples.countryinfo">
   <soapenv:Header/>
   <soapenv:Body>
      <web:ListOfCountryNamesByCode/>
   </soapenv:Body>
</soapenv:Envelope>]]></con:request><con:wsaConfig mustUnderstand="NONE" version="200508" action="http://www.oorsprong.org/websamples.countryinfo/CountryInfoServiceSoapType/ListOfCountryNamesByCodeRequest"/></con:call></con:operation><con:operation id="df38c978-1ae5-43dc-b0e1-7d437f4096a5" isOneWay="false" action="" name="ListOfCountryNamesByName" bindingOperationName="ListOfCountryNamesByName" type="Request-Response" inputName="" receivesAttachments="false" sendsAttachments="false" anonymous="optional"><con:settings/><con:call id="6ee88998-d89e-4681-8c3b-819e2df2d42f" name="Request 1"><con:settings/><con:encoding>UTF-8</con:encoding><con:endpoint>http://webservices.oorsprong.org/websamples.countryinfo/CountryInfoService.wso</con:endpoint><con:request><![CDATA[<soapenv:Envelope xmlns:soapenv="http://schemas.xmlsoap.org/soap/envelope/" xmlns:web="http://www.oorsprong.org/websamples.countryinfo">
   <soapenv:Header/>
   <soapenv:Body>
      <web:ListOfCountryNamesByName/>
   </soapenv:Body>
</soapenv:Envelope>]]></con:request><con:wsaConfig mustUnderstand="NONE" version="200508" action="http://www.oorsprong.org/websamples.countryinfo/CountryInfoServiceSoapType/ListOfCountryNamesByNameRequest"/></con:call></con:operation><con:operation id="55037d51-52c8-434e-a271-28ebe1ca1610" isOneWay="false" action="" name="ListOfCountryNamesGroupedByContinent" bindingOperationName="ListOfCountryNamesGroupedByContinent" type="Request-Response" inputName="" receivesAttachments="false" sendsAttachments="false" anonymous="optional"><con:settings/><con:call id="c2c52bf6-422a-42f8-9345-60d385bd0400" name="Request 1"><con:settings/><con:encoding>UTF-8</con:encoding><con:endpoint>http://webservices.oorsprong.org/websamples.countryinfo/CountryInfoService.wso</con:endpoint><con:request><![CDATA[<soapenv:Envelope xmlns:soapenv="http://schemas.xmlsoap.org/soap/envelope/" xmlns:web="http://www.oorsprong.org/websamples.countryinfo">
   <soapenv:Header/>
   <soapenv:Body>
      <web:ListOfCountryNamesGroupedByContinent/>
   </soapenv:Body>
</soapenv:Envelope>]]></con:request><con:wsaConfig mustUnderstand="NONE" version="200508" action="http://www.oorsprong.org/websamples.countryinfo/CountryInfoServiceSoapType/ListOfCountryNamesGroupedByContinentRequest"/></con:call></con:operation><con:operation id="b789a9a4-1ec1-4961-840c-05a40ec21d5f" isOneWay="false" action="" name="ListOfCurrenciesByCode" bindingOperationName="ListOfCurrenciesByCode" type="Request-Response" inputName="" receivesAttachments="false" sendsAttachments="false" anonymous="optional"><con:settings/><con:call id="9f7dfac2-ada6-4a6a-a186-229c1f633c4e" name="Request 1"><con:settings/><con:encoding>UTF-8</con:encoding><con:endpoint>http://webservices.oorsprong.org/websamples.countryinfo/CountryInfoService.wso</con:endpoint><con:request><![CDATA[<soapenv:Envelope xmlns:soapenv="http://schemas.xmlsoap.org/soap/envelope/" xmlns:web="http://www.oorsprong.org/websamples.countryinfo">
   <soapenv:Header/>
   <soapenv:Body>
      <web:ListOfCurrenciesByCode/>
   </soapenv:Body>
</soapenv:Envelope>]]></con:request><con:wsaConfig mustUnderstand="NONE" version="200508" action="http://www.oorsprong.org/websamples.countryinfo/CountryInfoServiceSoapType/ListOfCurrenciesByCodeRequest"/></con:call></con:operation><con:operation id="4135589d-0410-472d-9234-746f6eeb7802" isOneWay="false" action="" name="ListOfCurrenciesByName" bindingOperationName="ListOfCurrenciesByName" type="Request-Response" inputName="" receivesAttachments="false" sendsAttachments="false" anonymous="optional"><con:settings/><con:call id="8205778b-c0d6-4b85-898a-41d4ae82cf89" name="Request 1"><con:settings/><con:encoding>UTF-8</con:encoding><con:endpoint>http://webservices.oorsprong.org/websamples.countryinfo/CountryInfoService.wso</con:endpoint><con:request><![CDATA[<soapenv:Envelope xmlns:soapenv="http://schemas.xmlsoap.org/soap/envelope/" xmlns:web="http://www.oorsprong.org/websamples.countryinfo">
   <soapenv:Header/>
   <soapenv:Body>
      <web:ListOfCurrenciesByName/>
   </soapenv:Body>
</soapenv:Envelope>]]></con:request><con:wsaConfig mustUnderstand="NONE" version="200508" action="http://www.oorsprong.org/websamples.countryinfo/CountryInfoServiceSoapType/ListOfCurrenciesByNameRequest"/></con:call></con:operation><con:operation id="91b1ed49-22a5-44de-918a-7f71fa3c72d7" isOneWay="false" action="" name="ListOfLanguagesByCode" bindingOperationName="ListOfLanguagesByCode" type="Request-Response" inputName="" receivesAttachments="false" sendsAttachments="false" anonymous="optional"><con:settings/><con:call id="66971ffa-4103-4ebf-8060-b250a069fc5d" name="Request 1"><con:settings/><con:encoding>UTF-8</con:encoding><con:endpoint>http://webservices.oorsprong.org/websamples.countryinfo/CountryInfoService.wso</con:endpoint><con:request><![CDATA[<soapenv:Envelope xmlns:soapenv="http://schemas.xmlsoap.org/soap/envelope/" xmlns:web="http://www.oorsprong.org/websamples.countryinfo">
   <soapenv:Header/>
   <soapenv:Body>
      <web:ListOfLanguagesByCode/>
   </soapenv:Body>
</soapenv:Envelope>]]></con:request><con:wsaConfig mustUnderstand="NONE" version="200508" action="http://www.oorsprong.org/websamples.countryinfo/CountryInfoServiceSoapType/ListOfLanguagesByCodeRequest"/></con:call></con:operation><con:operation id="065dc9a2-dd0e-4161-b9b7-4682bc9b95c4" isOneWay="false" action="" name="ListOfLanguagesByName" bindingOperationName="ListOfLanguagesByName" type="Request-Response" inputName="" receivesAttachments="false" sendsAttachments="false" anonymous="optional"><con:settings/><con:call id="365c30e6-b0a4-4f92-9b85-772aa27d6072" name="Request 1"><con:settings/><con:encoding>UTF-8</con:encoding><con:endpoint>http://webservices.oorsprong.org/websamples.countryinfo/CountryInfoService.wso</con:endpoint><con:request><![CDATA[<soapenv:Envelope xmlns:soapenv="http://schemas.xmlsoap.org/soap/envelope/" xmlns:web="http://www.oorsprong.org/websamples.countryinfo">
   <soapenv:Header/>
   <soapenv:Body>
      <web:ListOfLanguagesByName/>
   </soapenv:Body>
</soapenv:Envelope>]]></con:request><con:wsaConfig mustUnderstand="NONE" version="200508" action="http://www.oorsprong.org/websamples.countryinfo/CountryInfoServiceSoapType/ListOfLanguagesByNameRequest"/></con:call></con:operation></con:interface><con:testSuite id="476ad36f-a49b-4987-88fd-625dbf9f1022" name="Sample_TestSuite"><con:settings/><con:runType>SEQUENTIAL</con:runType><con:testCase id="bc570a80-3417-4afe-9f95-4ddcb0516e5b" failOnError="true" failTestCaseOnErrors="true" keepSession="false" maxResults="0" name="CapitalCity TestCase" searchProperties="true"><con:settings/><con:testStep type="request" id="15594162-af5d-4553-b6fc-2800d289f10e" name="CapitalCity"><con:settings/><con:config xsi:type="con:RequestStep" xmlns:xsi="http://www.w3.org/2001/XMLSchema-instance"><con:interface>CountryInfoServiceSoapBinding</con:interface><con:operation>CapitalCity</con:operation><con:request name="CapitalCity" id="33153a55-7913-4f15-9fb8-71a1604b2bfb"><con:settings><con:setting id="com.eviware.soapui.impl.wsdl.WsdlRequest@request-headers">&lt;xml-fragment/></con:setting></con:settings><con:encoding>UTF-8</con:encoding><con:endpoint>http://webservices.oorsprong.org/websamples.countryinfo/CountryInfoService.wso</con:endpoint><con:request><![CDATA[<soapenv:Envelope xmlns:soapenv="http://schemas.xmlsoap.org/soap/envelope/" xmlns:web="http://www.oorsprong.org/websamples.countryinfo">
   <soapenv:Header/>
   <soapenv:Body>
      <web:CapitalCity>
         <web:sCountryISOCode>KE</web:sCountryISOCode>
      </web:CapitalCity>
   </soapenv:Body>
</soapenv:Envelope>]]></con:request><con:assertion type="Simple Contains"/><con:assertion type="Simple Contains" id="91211c7c-da5e-4a51-abf9-c3a0f42d3a7e" name="Contains"><con:configuration><token>Nairobi</token><ignoreCase>false</ignoreCase><useRegEx>false</useRegEx></con:configuration></con:assertion><con:credentials><con:authType>No Authorization</con:authType></con:credentials><con:jmsConfig JMSDeliveryMode="PERSISTENT"/><con:jmsPropertyConfig/><con:wsaConfig action="http://www.oorsprong.org/websamples.countryinfo/CountryInfoServiceSoapType/CapitalCityRequest" mustUnderstand="NONE" version="200508"/><con:wsrmConfig version="1.2"/></con:request></con:config></con:testStep><con:properties/></con:testCase><con:testCase id="92e436d0-1444-4da4-b457-f9642c4caf5b" failOnError="true" failTestCaseOnErrors="true" keepSession="false" maxResults="0" name="CountriesUsingCurrency TestCase" searchProperties="true"><con:settings/><con:testStep type="request" id="d5c23e9e-69d7-46b4-8d85-b372bcb2affd" name="CountriesUsingCurrency"><con:settings/><con:config xsi:type="con:RequestStep" xmlns:xsi="http://www.w3.org/2001/XMLSchema-instance"><con:interface>CountryInfoServiceSoapBinding</con:interface><con:operation>CountriesUsingCurrency</con:operation><con:request name="CountriesUsingCurrency" id="68bb8807-ac79-4ee7-846e-c910f06f2bfc"><con:settings/><con:encoding>UTF-8</con:encoding><con:endpoint>http://webservices.oorsprong.org/websamples.countryinfo/CountryInfoService.wso</con:endpoint><con:request><![CDATA[<soapenv:Envelope xmlns:soapenv="http://schemas.xmlsoap.org/soap/envelope/" xmlns:web="http://www.oorsprong.org/websamples.countryinfo">
   <soapenv:Header/>
   <soapenv:Body>
      <web:CountriesUsingCurrency>
         <web:sISOCurrencyCode>?</web:sISOCurrencyCode>
      </web:CountriesUsingCurrency>
   </soapenv:Body>
</soapenv:Envelope>]]></con:request><con:credentials><con:authType>No Authorization</con:authType></con:credentials><con:wsaConfig action="http://www.oorsprong.org/websamples.countryinfo/CountryInfoServiceSoapType/CountriesUsingCurrencyRequest"/></con:request></con:config></con:testStep><con:properties/></con:testCase><con:testCase id="c71bd808-40ff-48cb-a515-cbe74e88c418" failOnError="true" failTestCaseOnErrors="true" keepSession="false" maxResults="0" name="CountryCurrency TestCase" searchProperties="true"><con:settings/><con:testStep type="request" id="ab1db437-9df2-46f9-8fe7-90feb6fdfd70" name="CountryCurrency"><con:settings/><con:config xsi:type="con:RequestStep" xmlns:xsi="http://www.w3.org/2001/XMLSchema-instance"><con:interface>CountryInfoServiceSoapBinding</con:interface><con:operation>CountryCurrency</con:operation><con:request name="CountryCurrency" id="6bbf4147-8869-4e9c-97e2-bb983757cff2"><con:settings/><con:encoding>UTF-8</con:encoding><con:endpoint>http://webservices.oorsprong.org/websamples.countryinfo/CountryInfoService.wso</con:endpoint><con:request><![CDATA[<soapenv:Envelope xmlns:soapenv="http://schemas.xmlsoap.org/soap/envelope/" xmlns:web="http://www.oorsprong.org/websamples.countryinfo">
   <soapenv:Header/>
   <soapenv:Body>
      <web:CountryCurrency>
         <web:sCountryISOCode>?</web:sCountryISOCode>
      </web:CountryCurrency>
   </soapenv:Body>
</soapenv:Envelope>]]></con:request><con:credentials><con:authType>No Authorization</con:authType></con:credentials><con:wsaConfig action="http://www.oorsprong.org/websamples.countryinfo/CountryInfoServiceSoapType/CountryCurrencyRequest"/></con:request></con:config></con:testStep><con:properties/></con:testCase><con:testCase id="505152a2-5fa6-4b26-831c-1e2987d7faa7" failOnError="true" failTestCaseOnErrors="true" keepSession="false" maxResults="0" name="CountryFlag TestCase" searchProperties="true"><con:settings/><con:testStep type="request" id="5023a34c-65b3-4247-8fba-be666f5edc02" name="CountryFlag"><con:settings/><con:config xsi:type="con:RequestStep" xmlns:xsi="http://www.w3.org/2001/XMLSchema-instance"><con:interface>CountryInfoServiceSoapBinding</con:interface><con:operation>CountryFlag</con:operation><con:request name="CountryFlag" id="677e2ee4-b08b-4d8c-ae38-316e576de55e"><con:settings/><con:encoding>UTF-8</con:encoding><con:endpoint>http://webservices.oorsprong.org/websamples.countryinfo/CountryInfoService.wso</con:endpoint><con:request><![CDATA[<soapenv:Envelope xmlns:soapenv="http://schemas.xmlsoap.org/soap/envelope/" xmlns:web="http://www.oorsprong.org/websamples.countryinfo">
   <soapenv:Header/>
   <soapenv:Body>
      <web:CountryFlag>
         <web:sCountryISOCode>?</web:sCountryISOCode>
      </web:CountryFlag>
   </soapenv:Body>
</soapenv:Envelope>]]></con:request><con:credentials><con:authType>No Authorization</con:authType></con:credentials><con:wsaConfig action="http://www.oorsprong.org/websamples.countryinfo/CountryInfoServiceSoapType/CountryFlagRequest"/></con:request></con:config></con:testStep><con:properties/></con:testCase><con:testCase id="244f2f59-6cbc-4762-9e28-cb075ca4e53c" failOnError="true" failTestCaseOnErrors="true" keepSession="false" maxResults="0" name="CountryIntPhoneCode TestCase" searchProperties="true"><con:settings/><con:testStep type="request" id="ae960132-b2f5-44c1-8969-bbaa904651ae" name="CountryIntPhoneCode"><con:settings/><con:config xsi:type="con:RequestStep" xmlns:xsi="http://www.w3.org/2001/XMLSchema-instance"><con:interface>CountryInfoServiceSoapBinding</con:interface><con:operation>CountryIntPhoneCode</con:operation><con:request name="CountryIntPhoneCode" id="78e03436-60fb-43a6-b7a3-be50992783cb"><con:settings/><con:encoding>UTF-8</con:encoding><con:endpoint>http://webservices.oorsprong.org/websamples.countryinfo/CountryInfoService.wso</con:endpoint><con:request><![CDATA[<soapenv:Envelope xmlns:soapenv="http://schemas.xmlsoap.org/soap/envelope/" xmlns:web="http://www.oorsprong.org/websamples.countryinfo">
   <soapenv:Header/>
   <soapenv:Body>
      <web:CountryIntPhoneCode>
         <web:sCountryISOCode>?</web:sCountryISOCode>
      </web:CountryIntPhoneCode>
   </soapenv:Body>
</soapenv:Envelope>]]></con:request><con:credentials><con:authType>No Authorization</con:authType></con:credentials><con:wsaConfig action="http://www.oorsprong.org/websamples.countryinfo/CountryInfoServiceSoapType/CountryIntPhoneCodeRequest"/></con:request></con:config></con:testStep><con:properties/></con:testCase><con:testCase id="918d4dcc-c80a-4006-b462-49ccc824c5a0" failOnError="true" failTestCaseOnErrors="true" keepSession="false" maxResults="0" name="CountryISOCode TestCase" searchProperties="true"><con:settings/><con:testStep type="request" id="86b0ca43-021b-4611-846a-fcb8429ba07b" name="CountryISOCode"><con:settings/><con:config xsi:type="con:RequestStep" xmlns:xsi="http://www.w3.org/2001/XMLSchema-instance"><con:interface>CountryInfoServiceSoapBinding</con:interface><con:operation>CountryISOCode</con:operation><con:request name="CountryISOCode" id="57ce981c-ffdc-47d9-97ef-ad505c990595"><con:settings/><con:encoding>UTF-8</con:encoding><con:endpoint>http://webservices.oorsprong.org/websamples.countryinfo/CountryInfoService.wso</con:endpoint><con:request><![CDATA[<soapenv:Envelope xmlns:soapenv="http://schemas.xmlsoap.org/soap/envelope/" xmlns:web="http://www.oorsprong.org/websamples.countryinfo">
   <soapenv:Header/>
   <soapenv:Body>
      <web:CountryISOCode>
         <web:sCountryName>?</web:sCountryName>
      </web:CountryISOCode>
   </soapenv:Body>
</soapenv:Envelope>]]></con:request><con:credentials><con:authType>No Authorization</con:authType></con:credentials><con:wsaConfig action="http://www.oorsprong.org/websamples.countryinfo/CountryInfoServiceSoapType/CountryISOCodeRequest"/></con:request></con:config></con:testStep><con:properties/></con:testCase><con:testCase id="70c32415-9672-4907-a993-9f72eb0cded1" failOnError="true" failTestCaseOnErrors="true" keepSession="false" maxResults="0" name="CountryName TestCase" searchProperties="true"><con:settings/><con:testStep type="request" id="a620d815-001e-454d-a99a-6ed09caaccc9" name="CountryName"><con:settings/><con:config xsi:type="con:RequestStep" xmlns:xsi="http://www.w3.org/2001/XMLSchema-instance"><con:interface>CountryInfoServiceSoapBinding</con:interface><con:operation>CountryName</con:operation><con:request name="CountryName" id="eec4216a-9552-44ed-ac05-7155ecdfa3fd"><con:settings/><con:encoding>UTF-8</con:encoding><con:endpoint>http://webservices.oorsprong.org/websamples.countryinfo/CountryInfoService.wso</con:endpoint><con:request><![CDATA[<soapenv:Envelope xmlns:soapenv="http://schemas.xmlsoap.org/soap/envelope/" xmlns:web="http://www.oorsprong.org/websamples.countryinfo">
   <soapenv:Header/>
   <soapenv:Body>
      <web:CountryName>
         <web:sCountryISOCode>?</web:sCountryISOCode>
      </web:CountryName>
   </soapenv:Body>
</soapenv:Envelope>]]></con:request><con:credentials><con:authType>No Authorization</con:authType></con:credentials><con:wsaConfig action="http://www.oorsprong.org/websamples.countryinfo/CountryInfoServiceSoapType/CountryNameRequest"/></con:request></con:config></con:testStep><con:properties/></con:testCase><con:testCase id="585f7fbe-de79-4b16-ba4b-8caedfcea8c8" failOnError="true" failTestCaseOnErrors="true" keepSession="false" maxResults="0" name="CurrencyName TestCase" searchProperties="true"><con:settings/><con:testStep type="request" id="133eaa63-91d4-4788-8e7f-9cc14f7e3f32" name="CurrencyName"><con:settings/><con:config xsi:type="con:RequestStep" xmlns:xsi="http://www.w3.org/2001/XMLSchema-instance"><con:interface>CountryInfoServiceSoapBinding</con:interface><con:operation>CurrencyName</con:operation><con:request name="CurrencyName" id="5bc2c8cd-9545-4244-b605-abbbfbbc0c5d"><con:settings/><con:encoding>UTF-8</con:encoding><con:endpoint>http://webservices.oorsprong.org/websamples.countryinfo/CountryInfoService.wso</con:endpoint><con:request><![CDATA[<soapenv:Envelope xmlns:soapenv="http://schemas.xmlsoap.org/soap/envelope/" xmlns:web="http://www.oorsprong.org/websamples.countryinfo">
   <soapenv:Header/>
   <soapenv:Body>
      <web:CurrencyName>
         <web:sCurrencyISOCode>?</web:sCurrencyISOCode>
      </web:CurrencyName>
   </soapenv:Body>
</soapenv:Envelope>]]></con:request><con:credentials><con:authType>No Authorization</con:authType></con:credentials><con:wsaConfig action="http://www.oorsprong.org/websamples.countryinfo/CountryInfoServiceSoapType/CurrencyNameRequest"/></con:request></con:config></con:testStep><con:properties/></con:testCase><con:testCase id="aad98b09-dcde-4af7-ab57-1a3049b7771e" failOnError="true" failTestCaseOnErrors="true" keepSession="false" maxResults="0" name="FullCountryInfo TestCase" searchProperties="true"><con:settings/><con:testStep type="request" id="b0dc9957-012c-442b-9a9b-7f636c5036bf" name="FullCountryInfo"><con:settings/><con:config xsi:type="con:RequestStep" xmlns:xsi="http://www.w3.org/2001/XMLSchema-instance"><con:interface>CountryInfoServiceSoapBinding</con:interface><con:operation>FullCountryInfo</con:operation><con:request name="FullCountryInfo" id="97d201ec-e3ad-40b3-b2b3-8c0b083373de"><con:settings/><con:encoding>UTF-8</con:encoding><con:endpoint>http://webservices.oorsprong.org/websamples.countryinfo/CountryInfoService.wso</con:endpoint><con:request><![CDATA[<soapenv:Envelope xmlns:soapenv="http://schemas.xmlsoap.org/soap/envelope/" xmlns:web="http://www.oorsprong.org/websamples.countryinfo">
   <soapenv:Header/>
   <soapenv:Body>
      <web:FullCountryInfo>
         <web:sCountryISOCode>?</web:sCountryISOCode>
      </web:FullCountryInfo>
   </soapenv:Body>
</soapenv:Envelope>]]></con:request><con:credentials><con:authType>No Authorization</con:authType></con:credentials><con:wsaConfig action="http://www.oorsprong.org/websamples.countryinfo/CountryInfoServiceSoapType/FullCountryInfoRequest"/></con:request></con:config></con:testStep><con:properties/></con:testCase><con:testCase id="17620b03-e530-4173-82bd-4ba36518bc5d" failOnError="true" failTestCaseOnErrors="true" keepSession="false" maxResults="0" name="FullCountryInfoAllCountries TestCase" searchProperties="true"><con:settings/><con:testStep type="request" id="0d65f5d3-c01e-4bf1-8b9d-990fa90db66a" name="FullCountryInfoAllCountries"><con:settings/><con:config xsi:type="con:RequestStep" xmlns:xsi="http://www.w3.org/2001/XMLSchema-instance"><con:interface>CountryInfoServiceSoapBinding</con:interface><con:operation>FullCountryInfoAllCountries</con:operation><con:request name="FullCountryInfoAllCountries" id="1e95c452-2517-4443-9128-93f841096f3a"><con:settings/><con:encoding>UTF-8</con:encoding><con:endpoint>http://webservices.oorsprong.org/websamples.countryinfo/CountryInfoService.wso</con:endpoint><con:request><![CDATA[<soapenv:Envelope xmlns:soapenv="http://schemas.xmlsoap.org/soap/envelope/" xmlns:web="http://www.oorsprong.org/websamples.countryinfo">
   <soapenv:Header/>
   <soapenv:Body>
      <web:FullCountryInfoAllCountries/>
   </soapenv:Body>
</soapenv:Envelope>]]></con:request><con:credentials><con:authType>No Authorization</con:authType></con:credentials><con:wsaConfig action="http://www.oorsprong.org/websamples.countryinfo/CountryInfoServiceSoapType/FullCountryInfoAllCountriesRequest"/></con:request></con:config></con:testStep><con:properties/></con:testCase><con:testCase id="b6e9b080-11ea-441b-a8b5-b80418382565" failOnError="true" failTestCaseOnErrors="true" keepSession="false" maxResults="0" name="LanguageISOCode TestCase" searchProperties="true"><con:settings/><con:testStep type="request" id="18e685c4-44e7-49d0-ab8f-aa0ad7e2f577" name="LanguageISOCode"><con:settings/><con:config xsi:type="con:RequestStep" xmlns:xsi="http://www.w3.org/2001/XMLSchema-instance"><con:interface>CountryInfoServiceSoapBinding</con:interface><con:operation>LanguageISOCode</con:operation><con:request name="LanguageISOCode" id="bcc04275-f5d5-4ba1-b7f7-32a4f49aaa57"><con:settings/><con:encoding>UTF-8</con:encoding><con:endpoint>http://webservices.oorsprong.org/websamples.countryinfo/CountryInfoService.wso</con:endpoint><con:request><![CDATA[<soapenv:Envelope xmlns:soapenv="http://schemas.xmlsoap.org/soap/envelope/" xmlns:web="http://www.oorsprong.org/websamples.countryinfo">
   <soapenv:Header/>
   <soapenv:Body>
      <web:LanguageISOCode>
         <web:sLanguageName>?</web:sLanguageName>
      </web:LanguageISOCode>
   </soapenv:Body>
</soapenv:Envelope>]]></con:request><con:credentials><con:authType>No Authorization</con:authType></con:credentials><con:wsaConfig action="http://www.oorsprong.org/websamples.countryinfo/CountryInfoServiceSoapType/LanguageISOCodeRequest"/></con:request></con:config></con:testStep><con:properties/></con:testCase><con:testCase id="84ceef50-3967-40e0-9413-c01abe5abb91" failOnError="true" failTestCaseOnErrors="true" keepSession="false" maxResults="0" name="LanguageName TestCase" searchProperties="true"><con:settings/><con:testStep type="request" id="f5a66dc9-7819-499a-af2b-f1030b7a4c51" name="LanguageName"><con:settings/><con:config xsi:type="con:RequestStep" xmlns:xsi="http://www.w3.org/2001/XMLSchema-instance"><con:interface>CountryInfoServiceSoapBinding</con:interface><con:operation>LanguageName</con:operation><con:request name="LanguageName" id="bc78317c-88a6-479e-a1ae-d1319134cfcd"><con:settings/><con:encoding>UTF-8</con:encoding><con:endpoint>http://webservices.oorsprong.org/websamples.countryinfo/CountryInfoService.wso</con:endpoint><con:request><![CDATA[<soapenv:Envelope xmlns:soapenv="http://schemas.xmlsoap.org/soap/envelope/" xmlns:web="http://www.oorsprong.org/websamples.countryinfo">
   <soapenv:Header/>
   <soapenv:Body>
      <web:LanguageName>
         <web:sISOCode>?</web:sISOCode>
      </web:LanguageName>
   </soapenv:Body>
</soapenv:Envelope>]]></con:request><con:credentials><con:authType>No Authorization</con:authType></con:credentials><con:wsaConfig action="http://www.oorsprong.org/websamples.countryinfo/CountryInfoServiceSoapType/LanguageNameRequest"/></con:request></con:config></con:testStep><con:properties/></con:testCase><con:testCase id="63bb5120-8b41-460a-8057-9efaeb8dd635" failOnError="true" failTestCaseOnErrors="true" keepSession="false" maxResults="0" name="ListOfContinentsByCode TestCase" searchProperties="true"><con:settings/><con:testStep type="request" id="fcbf74ca-fd1d-4f5b-962d-a907ec89a49b" name="ListOfContinentsByCode"><con:settings/><con:config xsi:type="con:RequestStep" xmlns:xsi="http://www.w3.org/2001/XMLSchema-instance"><con:interface>CountryInfoServiceSoapBinding</con:interface><con:operation>ListOfContinentsByCode</con:operation><con:request name="ListOfContinentsByCode" id="4668257e-93e2-4efc-a7f8-318565a4fda3"><con:settings/><con:encoding>UTF-8</con:encoding><con:endpoint>http://webservices.oorsprong.org/websamples.countryinfo/CountryInfoService.wso</con:endpoint><con:request><![CDATA[<soapenv:Envelope xmlns:soapenv="http://schemas.xmlsoap.org/soap/envelope/" xmlns:web="http://www.oorsprong.org/websamples.countryinfo">
   <soapenv:Header/>
   <soapenv:Body>
      <web:ListOfContinentsByCode/>
   </soapenv:Body>
</soapenv:Envelope>]]></con:request><con:credentials><con:authType>No Authorization</con:authType></con:credentials><con:wsaConfig action="http://www.oorsprong.org/websamples.countryinfo/CountryInfoServiceSoapType/ListOfContinentsByCodeRequest"/></con:request></con:config></con:testStep><con:properties/></con:testCase><con:testCase id="e2e41982-809e-40a2-be66-65472f433256" failOnError="true" failTestCaseOnErrors="true" keepSession="false" maxResults="0" name="ListOfContinentsByName TestCase" searchProperties="true"><con:settings/><con:testStep type="request" id="f86c5642-eea6-463e-9c8b-6bd3e985bdf6" name="ListOfContinentsByName"><con:settings/><con:config xsi:type="con:RequestStep" xmlns:xsi="http://www.w3.org/2001/XMLSchema-instance"><con:interface>CountryInfoServiceSoapBinding</con:interface><con:operation>ListOfContinentsByName</con:operation><con:request name="ListOfContinentsByName" id="66f5c731-d83f-43c6-a4c5-7c9b2537c72f"><con:settings/><con:encoding>UTF-8</con:encoding><con:endpoint>http://webservices.oorsprong.org/websamples.countryinfo/CountryInfoService.wso</con:endpoint><con:request><![CDATA[<soapenv:Envelope xmlns:soapenv="http://schemas.xmlsoap.org/soap/envelope/" xmlns:web="http://www.oorsprong.org/websamples.countryinfo">
   <soapenv:Header/>
   <soapenv:Body>
      <web:ListOfContinentsByName/>
   </soapenv:Body>
</soapenv:Envelope>]]></con:request><con:credentials><con:authType>No Authorization</con:authType></con:credentials><con:wsaConfig action="http://www.oorsprong.org/websamples.countryinfo/CountryInfoServiceSoapType/ListOfContinentsByNameRequest"/></con:request></con:config></con:testStep><con:properties/></con:testCase><con:testCase id="a7ba0963-d467-4d6a-996b-0dcb5aef0adc" failOnError="true" failTestCaseOnErrors="true" keepSession="false" maxResults="0" name="ListOfCountryNamesByCode TestCase" searchProperties="true"><con:settings/><con:testStep type="request" id="deb10d6e-7b13-46b4-a1c9-ef70ce8805db" name="ListOfCountryNamesByCode"><con:settings/><con:config xsi:type="con:RequestStep" xmlns:xsi="http://www.w3.org/2001/XMLSchema-instance"><con:interface>CountryInfoServiceSoapBinding</con:interface><con:operation>ListOfCountryNamesByCode</con:operation><con:request name="ListOfCountryNamesByCode" id="5c66e69f-861a-4406-8e0f-55f3e6539fd9"><con:settings/><con:encoding>UTF-8</con:encoding><con:endpoint>http://webservices.oorsprong.org/websamples.countryinfo/CountryInfoService.wso</con:endpoint><con:request><![CDATA[<soapenv:Envelope xmlns:soapenv="http://schemas.xmlsoap.org/soap/envelope/" xmlns:web="http://www.oorsprong.org/websamples.countryinfo">
   <soapenv:Header/>
   <soapenv:Body>
      <web:ListOfCountryNamesByCode/>
   </soapenv:Body>
</soapenv:Envelope>]]></con:request><con:credentials><con:authType>No Authorization</con:authType></con:credentials><con:wsaConfig action="http://www.oorsprong.org/websamples.countryinfo/CountryInfoServiceSoapType/ListOfCountryNamesByCodeRequest"/></con:request></con:config></con:testStep><con:properties/></con:testCase><con:testCase id="6e8e15d2-ce02-40f8-982b-179f382dd360" failOnError="true" failTestCaseOnErrors="true" keepSession="false" maxResults="0" name="ListOfCountryNamesByName TestCase" searchProperties="true"><con:settings/><con:testStep type="request" id="aebd33b3-80f6-4925-81c9-c626035d9492" name="ListOfCountryNamesByName"><con:settings/><con:config xsi:type="con:RequestStep" xmlns:xsi="http://www.w3.org/2001/XMLSchema-instance"><con:interface>CountryInfoServiceSoapBinding</con:interface><con:operation>ListOfCountryNamesByName</con:operation><con:request name="ListOfCountryNamesByName" id="c513c6f2-e237-4bf3-8863-667ce2815fc0"><con:settings/><con:encoding>UTF-8</con:encoding><con:endpoint>http://webservices.oorsprong.org/websamples.countryinfo/CountryInfoService.wso</con:endpoint><con:request><![CDATA[<soapenv:Envelope xmlns:soapenv="http://schemas.xmlsoap.org/soap/envelope/" xmlns:web="http://www.oorsprong.org/websamples.countryinfo">
   <soapenv:Header/>
   <soapenv:Body>
      <web:ListOfCountryNamesByName/>
   </soapenv:Body>
</soapenv:Envelope>]]></con:request><con:credentials><con:authType>No Authorization</con:authType></con:credentials><con:wsaConfig action="http://www.oorsprong.org/websamples.countryinfo/CountryInfoServiceSoapType/ListOfCountryNamesByNameRequest"/></con:request></con:config></con:testStep><con:properties/></con:testCase><con:testCase id="293f565d-77c3-4916-9798-d96dc0ed4b39" failOnError="true" failTestCaseOnErrors="true" keepSession="false" maxResults="0" name="ListOfCountryNamesGroupedByContinent TestCase" searchProperties="true"><con:settings/><con:testStep type="request" id="30bb08d6-1cfe-40c3-9923-b92a7b12258d" name="ListOfCountryNamesGroupedByContinent"><con:settings/><con:config xsi:type="con:RequestStep" xmlns:xsi="http://www.w3.org/2001/XMLSchema-instance"><con:interface>CountryInfoServiceSoapBinding</con:interface><con:operation>ListOfCountryNamesGroupedByContinent</con:operation><con:request name="ListOfCountryNamesGroupedByContinent" id="2f9d26bd-c00f-4e86-b874-420cbb8e0be0"><con:settings/><con:encoding>UTF-8</con:encoding><con:endpoint>http://webservices.oorsprong.org/websamples.countryinfo/CountryInfoService.wso</con:endpoint><con:request><![CDATA[<soapenv:Envelope xmlns:soapenv="http://schemas.xmlsoap.org/soap/envelope/" xmlns:web="http://www.oorsprong.org/websamples.countryinfo">
   <soapenv:Header/>
   <soapenv:Body>
      <web:ListOfCountryNamesGroupedByContinent/>
   </soapenv:Body>
</soapenv:Envelope>]]></con:request><con:credentials><con:authType>No Authorization</con:authType></con:credentials><con:wsaConfig action="http://www.oorsprong.org/websamples.countryinfo/CountryInfoServiceSoapType/ListOfCountryNamesGroupedByContinentRequest"/></con:request></con:config></con:testStep><con:properties/></con:testCase><con:testCase id="8a7eda71-a950-4e9e-b33d-0ab356931f60" failOnError="true" failTestCaseOnErrors="true" keepSession="false" maxResults="0" name="ListOfCurrenciesByCode TestCase" searchProperties="true"><con:settings/><con:testStep type="request" id="57e66c99-ed5e-4284-9341-8062f295eb28" name="ListOfCurrenciesByCode"><con:settings/><con:config xsi:type="con:RequestStep" xmlns:xsi="http://www.w3.org/2001/XMLSchema-instance"><con:interface>CountryInfoServiceSoapBinding</con:interface><con:operation>ListOfCurrenciesByCode</con:operation><con:request name="ListOfCurrenciesByCode" id="ded6a1b0-0e99-41f8-a69c-323ca4db71db"><con:settings/><con:encoding>UTF-8</con:encoding><con:endpoint>http://webservices.oorsprong.org/websamples.countryinfo/CountryInfoService.wso</con:endpoint><con:request><![CDATA[<soapenv:Envelope xmlns:soapenv="http://schemas.xmlsoap.org/soap/envelope/" xmlns:web="http://www.oorsprong.org/websamples.countryinfo">
   <soapenv:Header/>
   <soapenv:Body>
      <web:ListOfCurrenciesByCode/>
   </soapenv:Body>
</soapenv:Envelope>]]></con:request><con:credentials><con:authType>No Authorization</con:authType></con:credentials><con:wsaConfig action="http://www.oorsprong.org/websamples.countryinfo/CountryInfoServiceSoapType/ListOfCurrenciesByCodeRequest"/></con:request></con:config></con:testStep><con:properties/></con:testCase><con:testCase id="9341f4e3-b9af-4932-bb2c-3a839d41a7ab" failOnError="true" failTestCaseOnErrors="true" keepSession="false" maxResults="0" name="ListOfCurrenciesByName TestCase" searchProperties="true"><con:settings/><con:testStep type="request" id="6fb435ab-3122-40e0-83e7-916e6e3e699d" name="ListOfCurrenciesByName"><con:settings/><con:config xsi:type="con:RequestStep" xmlns:xsi="http://www.w3.org/2001/XMLSchema-instance"><con:interface>CountryInfoServiceSoapBinding</con:interface><con:operation>ListOfCurrenciesByName</con:operation><con:request name="ListOfCurrenciesByName" id="ce1720ac-6b57-46b4-accd-571a99d06a7d"><con:settings/><con:encoding>UTF-8</con:encoding><con:endpoint>http://webservices.oorsprong.org/websamples.countryinfo/CountryInfoService.wso</con:endpoint><con:request><![CDATA[<soapenv:Envelope xmlns:soapenv="http://schemas.xmlsoap.org/soap/envelope/" xmlns:web="http://www.oorsprong.org/websamples.countryinfo">
   <soapenv:Header/>
   <soapenv:Body>
      <web:ListOfCurrenciesByName/>
   </soapenv:Body>
</soapenv:Envelope>]]></con:request><con:credentials><con:authType>No Authorization</con:authType></con:credentials><con:wsaConfig action="http://www.oorsprong.org/websamples.countryinfo/CountryInfoServiceSoapType/ListOfCurrenciesByNameRequest"/></con:request></con:config></con:testStep><con:properties/></con:testCase><con:testCase id="77f7dae5-ec09-49a0-81fe-e7f0683ccb08" failOnError="true" failTestCaseOnErrors="true" keepSession="false" maxResults="0" name="ListOfLanguagesByCode TestCase" searchProperties="true"><con:settings/><con:testStep type="request" id="8438cec4-109f-4e19-83e8-b869fa2556e0" name="ListOfLanguagesByCode"><con:settings/><con:config xsi:type="con:RequestStep" xmlns:xsi="http://www.w3.org/2001/XMLSchema-instance"><con:interface>CountryInfoServiceSoapBinding</con:interface><con:operation>ListOfLanguagesByCode</con:operation><con:request name="ListOfLanguagesByCode" id="aea6c914-cd68-450a-89ed-ce818615a59c"><con:settings/><con:encoding>UTF-8</con:encoding><con:endpoint>http://webservices.oorsprong.org/websamples.countryinfo/CountryInfoService.wso</con:endpoint><con:request><![CDATA[<soapenv:Envelope xmlns:soapenv="http://schemas.xmlsoap.org/soap/envelope/" xmlns:web="http://www.oorsprong.org/websamples.countryinfo">
   <soapenv:Header/>
   <soapenv:Body>
      <web:ListOfLanguagesByCode/>
   </soapenv:Body>
</soapenv:Envelope>]]></con:request><con:credentials><con:authType>No Authorization</con:authType></con:credentials><con:wsaConfig action="http://www.oorsprong.org/websamples.countryinfo/CountryInfoServiceSoapType/ListOfLanguagesByCodeRequest"/></con:request></con:config></con:testStep><con:properties/></con:testCase><con:testCase id="c43f4cb3-362b-4b79-873d-d46f6561f9f7" failOnError="true" failTestCaseOnErrors="true" keepSession="false" maxResults="0" name="ListOfLanguagesByName TestCase" searchProperties="true"><con:settings/><con:testStep type="request" id="2892660c-9d12-4019-a729-69f7857cf262" name="ListOfLanguagesByName"><con:settings/><con:config xsi:type="con:RequestStep" xmlns:xsi="http://www.w3.org/2001/XMLSchema-instance"><con:interface>CountryInfoServiceSoapBinding</con:interface><con:operation>ListOfLanguagesByName</con:operation><con:request name="ListOfLanguagesByName" id="adfe9ad4-b291-4cc0-b9f8-2645aecfa5c6"><con:settings/><con:encoding>UTF-8</con:encoding><con:endpoint>http://webservices.oorsprong.org/websamples.countryinfo/CountryInfoService.wso</con:endpoint><con:request><![CDATA[<soapenv:Envelope xmlns:soapenv="http://schemas.xmlsoap.org/soap/envelope/" xmlns:web="http://www.oorsprong.org/websamples.countryinfo">
   <soapenv:Header/>
   <soapenv:Body>
      <web:ListOfLanguagesByName/>
   </soapenv:Body>
</soapenv:Envelope>]]></con:request><con:credentials><con:authType>No Authorization</con:authType></con:credentials><con:wsaConfig action="http://www.oorsprong.org/websamples.countryinfo/CountryInfoServiceSoapType/ListOfLanguagesByNameRequest"/></con:request></con:config></con:testStep><con:properties/></con:testCase><con:properties/></con:testSuite><con:properties/><con:wssContainer/><con:oAuth2ProfileContainer/><con:oAuth1ProfileContainer/></con:soapui-project>